README.md
setup.py
scraperpy/__init__.py
scraperpy/__main__.py
scraperpy/browser.py
scraperpy/io.py
scraperpy/parsers.py
scraperpy/search.py
scraperpy/utils.py
scraperpy.egg-info/PKG-INFO
scraperpy.egg-info/SOURCES.txt
scraperpy.egg-info/dependency_links.txt
scraperpy.egg-info/top_level.txt