Metadata-Version: 1.0
Name: scraperpy
Version: 1.1.0
Summary: A simple package to make webscraping search engine results easy for PERSONAL projects only
Home-page: UNKNOWN
Author: Matt Eads
Author-email: matteads2@gmail.com
License: UNKNOWN
Project-URL: Source Code, https://github.com/meads2/scraper
Keywords: google web scraping parse
Platform: UNKNOWN
